setup.py
pyvote/__init__.py
pyvote/vote.py
pyvote.egg-info/PKG-INFO
pyvote.egg-info/SOURCES.txt
pyvote.egg-info/dependency_links.txt
pyvote.egg-info/requires.txt
pyvote.egg-info/top_level.txt