Metadata-Version: 1.1
Name: pyvote
Version: 0.0.1
Summary: Python voting with a redis backend
Home-page: http://pypi.python.org/pypi/pyvote
Author: Luis Morales
Author-email: luis.morales@legendarymonkey.com
License: UNKNOWN
Platform: UNKNOWN
Classifier: Development Status :: 2 - Pre-Alpha
Classifier: Intended Audience :: Developers
Classifier: Natural Language :: English
Classifier: License :: OSI Approved :: ISC License (ISCL)
Classifier: Programming Language :: Python
Classifier: Topic :: Utilities
